modelmachine/__about__.py
modelmachine/__init__.py
modelmachine/__main__.py
modelmachine/alu.py
modelmachine/cell.py
modelmachine/cli.py
modelmachine/io.py
modelmachine/ipython.py
modelmachine/cpu/__init__.py
modelmachine/cpu/cpu.py
modelmachine/cu/__init__.py
modelmachine/cu/control_unit.py
modelmachine/cu/control_unit_0.py
modelmachine/cu/control_unit_1.py
modelmachine/cu/control_unit_2.py
modelmachine/cu/control_unit_3.py
modelmachine/cu/control_unit_m.py
modelmachine/cu/control_unit_r.py
modelmachine/cu/control_unit_s.py
modelmachine/cu/control_unit_v.py
modelmachine/cu/halt_error.py
modelmachine/cu/opcode.py
modelmachine/cu/status.py
modelmachine/ide/__init__.py
modelmachine/ide/assemble.py
modelmachine/ide/common_parsing.py
modelmachine/ide/debug.py
modelmachine/ide/directive.py
modelmachine/ide/dump.py
modelmachine/ide/load.py
modelmachine/ide/source.py
modelmachine/ide/user_config.py
modelmachine/ide/asm/__init__.py
modelmachine/ide/asm/asm.py
modelmachine/ide/asm/errors.py
modelmachine/ide/asm/operand.py
modelmachine/ide/asm/opcode_table/__init__.py
modelmachine/ide/asm/opcode_table/mm0.py
modelmachine/ide/asm/opcode_table/mm1.py
modelmachine/ide/asm/opcode_table/mm2.py
modelmachine/ide/asm/opcode_table/mm3.py
modelmachine/ide/asm/opcode_table/mmm.py
modelmachine/ide/asm/opcode_table/mmr.py
modelmachine/ide/asm/opcode_table/mms.py
modelmachine/ide/asm/opcode_table/mmv.py
modelmachine/memory/__init__.py
modelmachine/memory/ram.py
modelmachine/memory/register.py
modelmachine/prompt/__init__.py
modelmachine/prompt/colors.py
modelmachine/prompt/is_interactive.py
modelmachine/prompt/prompt.py
modelmachine/shared/__init__.py
modelmachine/shared/enum_mixin.py
modelmachine/shared/insort_range.py
modelmachine-0.2.6.dist-info/METADATA
modelmachine-0.2.6.dist-info/WHEEL
modelmachine-0.2.6.dist-info/entry_points.txt
modelmachine-0.2.6.dist-info/licenses/LICENSE.txt
modelmachine-0.2.6.dist-info/RECORD
