Metadata-Version: 2.4
Name: modelmachine
Version: 0.2.6
Summary: Model machine emulator
Project-URL: Homepage, https://github.com/cmc-python/modelmachine
Project-URL: Repository, https://github.com/cmc-python/modelmachine.git
Project-URL: Documentation, https://github.com/cmc-python/modelmachine#readme
Project-URL: Issues, https://github.com/cmc-python/modelmachine/issues
Project-URL: Changelog, https://github.com/cmc-python/modelmachine/releases
Maintainer-email: Vladimir Liutov <vs@lutov.net>, "Fr. Br. George" <georgle@altlinux.org>
License:             DO WHAT THE FUCK YOU WANT TO PUBLIC LICENSE
License-File: LICENSE.txt
Classifier: Development Status :: 2 - Pre-Alpha
Classifier: Environment :: Console
Classifier: Intended Audience :: Education
Classifier: Natural Language :: English
Classifier: Natural Language :: Russian
Classifier: Operating System :: Microsoft :: Windows
Classifier: Operating System :: Unix
Classifier: Programming Language :: Python :: 3 :: Only
Classifier: Topic :: Education
Classifier: Topic :: Scientific/Engineering
Classifier: Topic :: Utilities
Requires-Python: >=3.7
Requires-Dist: pyparsing==3.1.4
Requires-Dist: tomli~=2.0; python_version < '3.11'
